{
  "generated_at": "2025-12-11T09:18:58.715275Z",
  "recs": [
    {
      "symbol": "BRENT",
      "acao": "comprar",
      "score": 2.7,
      "confianca": 77,
      "razoes": [
        {
          "title": "US says it seized oil tanker off Venezuela coast",
          "url": "https://www.aljazeera.com/video/newsfeed/2025/12/11/us-says-it-seized-oil-tanker-off-venezuela-coast?traffic_source=rss"
        },
        {
          "title": "South Sudan army to secure critical Heglig oilfield in Sudan war spillover",
          "url": "https://www.aljazeera.com/news/2025/12/11/south-sudan-army-to-secure-critical-heglig-oilfield-in-sudan-war-spillover?traffic_source=rss"
        }
      ],
      "chg1d": 0.0,
      "chg5d": 0.0,
      "chg1m": 0.0
    },
    {
      "symbol": "XLE",
      "acao": "comprar",
      "score": 2.7,
      "confianca": 77,
      "razoes": [
        {
          "title": "US says it seized oil tanker off Venezuela coast",
          "url": "https://www.aljazeera.com/video/newsfeed/2025/12/11/us-says-it-seized-oil-tanker-off-venezuela-coast?traffic_source=rss"
        },
        {
          "title": "South Sudan army to secure critical Heglig oilfield in Sudan war spillover",
          "url": "https://www.aljazeera.com/news/2025/12/11/south-sudan-army-to-secure-critical-heglig-oilfield-in-sudan-war-spillover?traffic_source=rss"
        }
      ],
      "chg1d": 0.01050328227571109,
      "chg5d": -0.497114232821518,
      "chg1m": -0.48887659103486436
    },
    {
      "symbol": "SOXX",
      "acao": "observar",
      "score": 0.84,
      "confianca": 24,
      "razoes": [
        {
          "title": "US Congress advances bill to nix Caesar Act sanctions on Syria",
          "url": "https://www.aljazeera.com/news/2025/12/11/us-congress-advances-bill-to-nix-caesar-act-sanctions-on-syria?traffic_source=rss"
        }
      ],
      "chg1d": 0.013293612659363114,
      "chg5d": 0.022530385311610973,
      "chg1m": 0.04745033112582776
    },
    {
      "symbol": "ASML.AS",
      "acao": "observar",
      "score": 0.84,
      "confianca": 24,
      "razoes": [
        {
          "title": "US Congress advances bill to nix Caesar Act sanctions on Syria",
          "url": "https://www.aljazeera.com/news/2025/12/11/us-congress-advances-bill-to-nix-caesar-act-sanctions-on-syria?traffic_source=rss"
        }
      ],
      "chg1d": 0.0070899013891886934,
      "chg5d": -0.018932089892367682,
      "chg1m": 0.07752288720530615
    },
    {
      "symbol": "TSM",
      "acao": "observar",
      "score": 0.84,
      "confianca": 24,
      "razoes": [
        {
          "title": "US Congress advances bill to nix Caesar Act sanctions on Syria",
          "url": "https://www.aljazeera.com/news/2025/12/11/us-congress-advances-bill-to-nix-caesar-act-sanctions-on-syria?traffic_source=rss"
        }
      ],
      "chg1d": 0.02218120694769441,
      "chg5d": 0.049720764934845146,
      "chg1m": 0.05036068682900398
    }
  ]
}