{
  "generated_at": "2026-06-13T06:51:21.138541Z",
  "recs": [
    {
      "symbol": "LMT",
      "acao": "comprar",
      "score": 3.42,
      "confianca": 95,
      "razoes": [
        {
          "title": "Iran war live: US, Tehran signal peace deal within reach but not signed yet",
          "url": "https://www.aljazeera.com/news/liveblog/2026/6/13/iran-war-live-us-tehran-signal-peace-deal-within-reach-but-not-signed-yet?traffic_source=rss"
        },
        {
          "title": "UAE to unlock frozen Iranian funds amid US ceasefire push: Sources",
          "url": "https://www.aljazeera.com/news/2026/6/12/uae-to-unlock-frozen-iranian-funds-amid-us-ceasefire-push?traffic_source=rss"
        },
        {
          "title": "Will there be a deal to end the Iran war this time?",
          "url": "https://www.aljazeera.com/video/inside-story/2026/6/12/will-there-be-a-deal-to-end-the-iran-war-this-time?traffic_source=rss"
        },
        {
          "title": "US Congressman says Trump won’t send loads of money to Iran",
          "url": "https://www.aljazeera.com/video/newsfeed/2026/6/12/us-congressman-says-trump-wont-send-loads-of-money-to-iran?traffic_source=rss"
        }
      ],
      "chg1d": 0.0,
      "chg5d": 0.0,
      "chg1m": 0.0
    },
    {
      "symbol": "XLE",
      "acao": "comprar",
      "score": 3.42,
      "confianca": 95,
      "razoes": [
        {
          "title": "Iran war live: US, Tehran signal peace deal within reach but not signed yet",
          "url": "https://www.aljazeera.com/news/liveblog/2026/6/13/iran-war-live-us-tehran-signal-peace-deal-within-reach-but-not-signed-yet?traffic_source=rss"
        },
        {
          "title": "UAE to unlock frozen Iranian funds amid US ceasefire push: Sources",
          "url": "https://www.aljazeera.com/news/2026/6/12/uae-to-unlock-frozen-iranian-funds-amid-us-ceasefire-push?traffic_source=rss"
        },
        {
          "title": "Will there be a deal to end the Iran war this time?",
          "url": "https://www.aljazeera.com/video/inside-story/2026/6/12/will-there-be-a-deal-to-end-the-iran-war-this-time?traffic_source=rss"
        },
        {
          "title": "US Congressman says Trump won’t send loads of money to Iran",
          "url": "https://www.aljazeera.com/video/newsfeed/2026/6/12/us-congressman-says-trump-wont-send-loads-of-money-to-iran?traffic_source=rss"
        }
      ],
      "chg1d": 0.0,
      "chg5d": 0.0,
      "chg1m": 0.0
    },
    {
      "symbol": "BRENT",
      "acao": "comprar",
      "score": 3.42,
      "confianca": 95,
      "razoes": [
        {
          "title": "Iran war live: US, Tehran signal peace deal within reach but not signed yet",
          "url": "https://www.aljazeera.com/news/liveblog/2026/6/13/iran-war-live-us-tehran-signal-peace-deal-within-reach-but-not-signed-yet?traffic_source=rss"
        },
        {
          "title": "UAE to unlock frozen Iranian funds amid US ceasefire push: Sources",
          "url": "https://www.aljazeera.com/news/2026/6/12/uae-to-unlock-frozen-iranian-funds-amid-us-ceasefire-push?traffic_source=rss"
        },
        {
          "title": "Will there be a deal to end the Iran war this time?",
          "url": "https://www.aljazeera.com/video/inside-story/2026/6/12/will-there-be-a-deal-to-end-the-iran-war-this-time?traffic_source=rss"
        },
        {
          "title": "US Congressman says Trump won’t send loads of money to Iran",
          "url": "https://www.aljazeera.com/video/newsfeed/2026/6/12/us-congressman-says-trump-wont-send-loads-of-money-to-iran?traffic_source=rss"
        }
      ],
      "chg1d": 0.0,
      "chg5d": 0.0,
      "chg1m": 0.0
    }
  ]
}