{
  "generated_at": "2025-09-27T06:15:34.274732Z",
  "recs": [
    {
      "symbol": "XLE",
      "acao": "comprar",
      "score": 4.85,
      "confianca": 95,
      "razoes": [
        {
          "title": "Turkiye, group of athletes call on FIFA, UEFA to ban Israel’s football team",
          "url": "https://www.aljazeera.com/news/2025/9/27/turkiye-group-of-athletes-call-on-fifa-uefa-to-ban-israels-football-team?traffic_source=rss"
        },
        {
          "title": "UN sanctions on Iran set to return after failed delay bid",
          "url": "https://www.aljazeera.com/video/newsfeed/2025/9/26/un-sanctions-on-iran-set-to-return-after-failed-delay-bid?traffic_source=rss"
        },
        {
          "title": "Omer Bartov on Gaza genocide and Israel’s history of occupation",
          "url": "https://www.aljazeera.com/video/upfront/2025/9/26/omer-bartov-on-gaza-genocide-and-israels-history-of-occupation?traffic_source=rss"
        },
        {
          "title": "Recognising Palestine vs holding Israel accountable?",
          "url": "https://www.aljazeera.com/video/the-bottom-line/2025/9/26/recognising-palestine-vs-holding-israel-accountable?traffic_source=rss"
        },
        {
          "title": "‘Beyond humanity’: Israeli strike devastates Gaza City neighbourhood",
          "url": "https://www.aljazeera.com/video/newsfeed/2025/9/26/beyond-humanity-israeli-strike-devastates-gaza-city-neighbourhood?traffic_source=rss"
        }
      ],
      "chg1d": 0.009215578716401418,
      "chg5d": 0.03920018075011296,
      "chg1m": 0.031046850481954675
    },
    {
      "symbol": "LMT",
      "acao": "comprar",
      "score": 4.85,
      "confianca": 95,
      "razoes": [
        {
          "title": "Turkiye, group of athletes call on FIFA, UEFA to ban Israel’s football team",
          "url": "https://www.aljazeera.com/news/2025/9/27/turkiye-group-of-athletes-call-on-fifa-uefa-to-ban-israels-football-team?traffic_source=rss"
        },
        {
          "title": "UN sanctions on Iran set to return after failed delay bid",
          "url": "https://www.aljazeera.com/video/newsfeed/2025/9/26/un-sanctions-on-iran-set-to-return-after-failed-delay-bid?traffic_source=rss"
        },
        {
          "title": "Omer Bartov on Gaza genocide and Israel’s history of occupation",
          "url": "https://www.aljazeera.com/video/upfront/2025/9/26/omer-bartov-on-gaza-genocide-and-israels-history-of-occupation?traffic_source=rss"
        },
        {
          "title": "Recognising Palestine vs holding Israel accountable?",
          "url": "https://www.aljazeera.com/video/the-bottom-line/2025/9/26/recognising-palestine-vs-holding-israel-accountable?traffic_source=rss"
        },
        {
          "title": "‘Beyond humanity’: Israeli strike devastates Gaza City neighbourhood",
          "url": "https://www.aljazeera.com/video/newsfeed/2025/9/26/beyond-humanity-israeli-strike-devastates-gaza-city-neighbourhood?traffic_source=rss"
        }
      ],
      "chg1d": 0.0064004624850312235,
      "chg5d": 0.03065928024696579,
      "chg1m": 0.07254604264307868
    },
    {
      "symbol": "BRENT",
      "acao": "comprar",
      "score": 4.85,
      "confianca": 95,
      "razoes": [
        {
          "title": "Turkiye, group of athletes call on FIFA, UEFA to ban Israel’s football team",
          "url": "https://www.aljazeera.com/news/2025/9/27/turkiye-group-of-athletes-call-on-fifa-uefa-to-ban-israels-football-team?traffic_source=rss"
        },
        {
          "title": "UN sanctions on Iran set to return after failed delay bid",
          "url": "https://www.aljazeera.com/video/newsfeed/2025/9/26/un-sanctions-on-iran-set-to-return-after-failed-delay-bid?traffic_source=rss"
        },
        {
          "title": "Omer Bartov on Gaza genocide and Israel’s history of occupation",
          "url": "https://www.aljazeera.com/video/upfront/2025/9/26/omer-bartov-on-gaza-genocide-and-israels-history-of-occupation?traffic_source=rss"
        },
        {
          "title": "Recognising Palestine vs holding Israel accountable?",
          "url": "https://www.aljazeera.com/video/the-bottom-line/2025/9/26/recognising-palestine-vs-holding-israel-accountable?traffic_source=rss"
        },
        {
          "title": "‘Beyond humanity’: Israeli strike devastates Gaza City neighbourhood",
          "url": "https://www.aljazeera.com/video/newsfeed/2025/9/26/beyond-humanity-israeli-strike-devastates-gaza-city-neighbourhood?traffic_source=rss"
        }
      ],
      "chg1d": 0.0,
      "chg5d": 0.0,
      "chg1m": 0.0
    },
    {
      "symbol": "TSM",
      "acao": "comprar",
      "score": 3.36,
      "confianca": 95,
      "razoes": [
        {
          "title": "UN sanctions on Iran set to return after failed delay bid",
          "url": "https://www.aljazeera.com/video/newsfeed/2025/9/26/un-sanctions-on-iran-set-to-return-after-failed-delay-bid?traffic_source=rss"
        },
        {
          "title": "Protests, calls for sanctions greet Netanyahu at UN amid Gaza horrors",
          "url": "https://www.aljazeera.com/news/2025/9/26/protests-calls-for-sanctions-greet-netanyahu-at-un-amid-gaza-horrors?traffic_source=rss"
        },
        {
          "title": "China hails multilateralism, takes digs at US tariffs",
          "url": "https://www.aljazeera.com/video/newsfeed/2025/9/26/china-hails-multilateralism-takes-digs-at-us-tariffs?traffic_source=rss"
        },
        {
          "title": "Sanctions against Iran set to snap back after UN Security Council vote",
          "url": "https://www.aljazeera.com/news/2025/9/26/u-n-security-council-rejects-last-ditch-effort-to-delay-iran-sanctions?traffic_source=rss"
        }
      ],
      "chg1d": -0.011927998265018475,
      "chg5d": 0.032053460188016795,
      "chg1m": 0.14237953947093496
    },
    {
      "symbol": "SOXX",
      "acao": "comprar",
      "score": 3.36,
      "confianca": 95,
      "razoes": [
        {
          "title": "UN sanctions on Iran set to return after failed delay bid",
          "url": "https://www.aljazeera.com/video/newsfeed/2025/9/26/un-sanctions-on-iran-set-to-return-after-failed-delay-bid?traffic_source=rss"
        },
        {
          "title": "Protests, calls for sanctions greet Netanyahu at UN amid Gaza horrors",
          "url": "https://www.aljazeera.com/news/2025/9/26/protests-calls-for-sanctions-greet-netanyahu-at-un-amid-gaza-horrors?traffic_source=rss"
        },
        {
          "title": "China hails multilateralism, takes digs at US tariffs",
          "url": "https://www.aljazeera.com/video/newsfeed/2025/9/26/china-hails-multilateralism-takes-digs-at-us-tariffs?traffic_source=rss"
        },
        {
          "title": "Sanctions against Iran set to snap back after UN Security Council vote",
          "url": "https://www.aljazeera.com/news/2025/9/26/u-n-security-council-rejects-last-ditch-effort-to-delay-iran-sanctions?traffic_source=rss"
        }
      ],
      "chg1d": 0.0021995228153891106,
      "chg5d": 0.011171293161814377,
      "chg1m": 0.06958701360706605
    },
    {
      "symbol": "ASML.AS",
      "acao": "comprar",
      "score": 3.36,
      "confianca": 95,
      "razoes": [
        {
          "title": "UN sanctions on Iran set to return after failed delay bid",
          "url": "https://www.aljazeera.com/video/newsfeed/2025/9/26/un-sanctions-on-iran-set-to-return-after-failed-delay-bid?traffic_source=rss"
        },
        {
          "title": "Protests, calls for sanctions greet Netanyahu at UN amid Gaza horrors",
          "url": "https://www.aljazeera.com/news/2025/9/26/protests-calls-for-sanctions-greet-netanyahu-at-un-amid-gaza-horrors?traffic_source=rss"
        },
        {
          "title": "China hails multilateralism, takes digs at US tariffs",
          "url": "https://www.aljazeera.com/video/newsfeed/2025/9/26/china-hails-multilateralism-takes-digs-at-us-tariffs?traffic_source=rss"
        },
        {
          "title": "Sanctions against Iran set to snap back after UN Security Council vote",
          "url": "https://www.aljazeera.com/news/2025/9/26/u-n-security-council-rejects-last-ditch-effort-to-delay-iran-sanctions?traffic_source=rss"
        }
      ],
      "chg1d": 0.0020746669475014768,
      "chg5d": 0.020779917395269007,
      "chg1m": 0.23574025974025972
    },
    {
      "symbol": "EUROSTOXX50",
      "acao": "observar",
      "score": 0.97,
      "confianca": 27,
      "razoes": [
        {
          "title": "Interest rate cut offers hope to Canada’s sluggish housing market",
          "url": "https://www.aljazeera.com/economy/2025/9/26/interest-rate-cut-offers-hope-to-canadas-sluggish-housing-market?traffic_source=rss"
        }
      ],
      "chg1d": 0.0,
      "chg5d": 0.0,
      "chg1m": 0.0
    },
    {
      "symbol": "SPY",
      "acao": "observar",
      "score": 0.97,
      "confianca": 27,
      "razoes": [
        {
          "title": "Interest rate cut offers hope to Canada’s sluggish housing market",
          "url": "https://www.aljazeera.com/economy/2025/9/26/interest-rate-cut-offers-hope-to-canadas-sluggish-housing-market?traffic_source=rss"
        }
      ],
      "chg1d": 0.0057290479446852,
      "chg5d": -0.0028326050926623402,
      "chg1m": 0.023491022686853463
    },
    {
      "symbol": "IWM",
      "acao": "observar",
      "score": 0.97,
      "confianca": 27,
      "razoes": [
        {
          "title": "Interest rate cut offers hope to Canada’s sluggish housing market",
          "url": "https://www.aljazeera.com/economy/2025/9/26/interest-rate-cut-offers-hope-to-canadas-sluggish-housing-market?traffic_source=rss"
        }
      ],
      "chg1d": 0.008567010740106195,
      "chg5d": -0.0067495267100172295,
      "chg1m": 0.02288717470543361
    },
    {
      "symbol": "QQQ",
      "acao": "observar",
      "score": 0.97,
      "confianca": 27,
      "razoes": [
        {
          "title": "Interest rate cut offers hope to Canada’s sluggish housing market",
          "url": "https://www.aljazeera.com/economy/2025/9/26/interest-rate-cut-offers-hope-to-canadas-sluggish-housing-market?traffic_source=rss"
        }
      ],
      "chg1d": 0.0041109969167524045,
      "chg5d": -0.005639442729623751,
      "chg1m": 0.0391985910826693
    }
  ]
}