{
  "generated_at": "2026-02-27T21:21:30.620168Z",
  "recs": [
    {
      "symbol": "LMT",
      "acao": "comprar",
      "score": 5.44,
      "confianca": 95,
      "razoes": [
        {
          "title": "IAEA urges Iran to allow inspections, points at Isfahan",
          "url": "https://www.aljazeera.com/news/2026/2/27/iaea-eyes-isfahan-nuclear-complex-as-it-urges-iran-to-allow?traffic_source=rss"
        },
        {
          "title": "Oman’s foreign minister meets with US’s Vance as Middle East tensions rise",
          "url": "https://www.aljazeera.com/news/2026/2/27/omans-foreign-minister-meets-with-uss-vance-as-middle-east-tensions-rise?traffic_source=rss"
        },
        {
          "title": "Rubio plans Israel trip as Trump says he’s ‘not happy’ with US-Iran talks",
          "url": "https://www.aljazeera.com/news/2026/2/27/marco-rubio-plans-israel-trip-as-trump-says-hes-not-happy-with-iran-talk?traffic_source=rss"
        },
        {
          "title": "Israel’s top court allows aid groups facing Gaza ban to continue working",
          "url": "https://www.aljazeera.com/news/2026/2/27/israels-top-court-allows-aid-groups-facing-gaza-ban-to-continue-working?traffic_source=rss"
        },
        {
          "title": "Iran says US must drop ‘excessive demands’ in nuclear negotiations",
          "url": "https://www.aljazeera.com/news/2026/2/27/iran-says-us-must-drop-excessive-demands-in-nuclear-negotiations?traffic_source=rss"
        }
      ],
      "chg1d": 0.025637828655144003,
      "chg5d": -0.00027344818156951656,
      "chg1m": 0.1018132502888142
    },
    {
      "symbol": "BRENT",
      "acao": "comprar",
      "score": 5.44,
      "confianca": 95,
      "razoes": [
        {
          "title": "IAEA urges Iran to allow inspections, points at Isfahan",
          "url": "https://www.aljazeera.com/news/2026/2/27/iaea-eyes-isfahan-nuclear-complex-as-it-urges-iran-to-allow?traffic_source=rss"
        },
        {
          "title": "Oman’s foreign minister meets with US’s Vance as Middle East tensions rise",
          "url": "https://www.aljazeera.com/news/2026/2/27/omans-foreign-minister-meets-with-uss-vance-as-middle-east-tensions-rise?traffic_source=rss"
        },
        {
          "title": "Rubio plans Israel trip as Trump says he’s ‘not happy’ with US-Iran talks",
          "url": "https://www.aljazeera.com/news/2026/2/27/marco-rubio-plans-israel-trip-as-trump-says-hes-not-happy-with-iran-talk?traffic_source=rss"
        },
        {
          "title": "Israel’s top court allows aid groups facing Gaza ban to continue working",
          "url": "https://www.aljazeera.com/news/2026/2/27/israels-top-court-allows-aid-groups-facing-gaza-ban-to-continue-working?traffic_source=rss"
        },
        {
          "title": "Iran says US must drop ‘excessive demands’ in nuclear negotiations",
          "url": "https://www.aljazeera.com/news/2026/2/27/iran-says-us-must-drop-excessive-demands-in-nuclear-negotiations?traffic_source=rss"
        }
      ],
      "chg1d": 0.0,
      "chg5d": 0.0,
      "chg1m": 0.0
    },
    {
      "symbol": "XLE",
      "acao": "comprar",
      "score": 5.44,
      "confianca": 95,
      "razoes": [
        {
          "title": "IAEA urges Iran to allow inspections, points at Isfahan",
          "url": "https://www.aljazeera.com/news/2026/2/27/iaea-eyes-isfahan-nuclear-complex-as-it-urges-iran-to-allow?traffic_source=rss"
        },
        {
          "title": "Oman’s foreign minister meets with US’s Vance as Middle East tensions rise",
          "url": "https://www.aljazeera.com/news/2026/2/27/omans-foreign-minister-meets-with-uss-vance-as-middle-east-tensions-rise?traffic_source=rss"
        },
        {
          "title": "Rubio plans Israel trip as Trump says he’s ‘not happy’ with US-Iran talks",
          "url": "https://www.aljazeera.com/news/2026/2/27/marco-rubio-plans-israel-trip-as-trump-says-hes-not-happy-with-iran-talk?traffic_source=rss"
        },
        {
          "title": "Israel’s top court allows aid groups facing Gaza ban to continue working",
          "url": "https://www.aljazeera.com/news/2026/2/27/israels-top-court-allows-aid-groups-facing-gaza-ban-to-continue-working?traffic_source=rss"
        },
        {
          "title": "Iran says US must drop ‘excessive demands’ in nuclear negotiations",
          "url": "https://www.aljazeera.com/news/2026/2/27/iran-says-us-must-drop-excessive-demands-in-nuclear-negotiations?traffic_source=rss"
        }
      ],
      "chg1d": 0.015803814713896542,
      "chg5d": 0.01895043731778424,
      "chg1m": 0.11728271728271739
    }
  ]
}